logger_lib/__init__.py
logger_lib/logger.py
logger_lib-0.2.0.dist-info/METADATA
logger_lib-0.2.0.dist-info/WHEEL
logger_lib-0.2.0.dist-info/top_level.txt
logger_lib-0.2.0.dist-info/RECORD
