Metadata-Version: 2.1
Name: logger-lib
Version: 0.2.0
Summary: Logger Library for Gauge Test
Home-page: UNKNOWN
Author: UNKNOWN
Author-email: UNKNOWN
License: UNKNOWN
Platform: UNKNOWN
Requires-Dist: wheel
Requires-Dist: colorlog
